omnilogger/__init__.py
omnilogger/database.py
omnilogger/input_validation.py
omnilogger/logger.py
omnilogger-0.0.4.dist-info/LICENSE
omnilogger-0.0.4.dist-info/METADATA
omnilogger-0.0.4.dist-info/WHEEL
omnilogger-0.0.4.dist-info/RECORD
