Metadata-Version: 2.1
Name: omnilogger
Version: 0.0.4
Summary: logger for LLM conversations
Author: Callum Hemsley
Author-email: callumh@theodo.co.uk
Requires-Python: >=3.7.1,<4.0.0
Classifier: License :: OSI Approved :: MIT License
Classifier: Operating System :: OS Independent
Classifier: Programming Language :: Python :: 3
Classifier: Programming Language :: Python :: 3.8
Classifier: Programming Language :: Python :: 3.9
Classifier: Programming Language :: Python :: 3.10
Classifier: Programming Language :: Python :: 3.11
Requires-Dist: openai (>=0.27.8,<0.28.0)
Requires-Dist: psycopg2-binary (>=2.9.7,<3.0.0)
